{"is_source_file": false, "format": null, "description": "", "external_files": [], "external_methods": [], "published": [], "classes": [], "methods": [], "calls": [], "search-terms": [], "state": 2, "file_id": 9, "knowledge_revision": 35, "git_revision": "d6b68505d221a78fa26211651ba87c4e59c9a288", "hash": "171a82c1b66c3c6d4bbf669bcd7167bc", "format-version": 4, "code-base-name": "ticc_tac_toe_frontend", "filename": "ticc_tac_toe_frontend/src/App.css", "revision_history": [{"35": "d6b68505d221a78fa26211651ba87c4e59c9a288"}]}